helloworld.py
helloworld_mytest-0.1.3.dist-info/LICENSE.txt
helloworld_mytest-0.1.3.dist-info/METADATA
helloworld_mytest-0.1.3.dist-info/RECORD
helloworld_mytest-0.1.3.dist-info/WHEEL
helloworld_mytest-0.1.3.dist-info/top_level.txt
