Metadata-Version: 2.1
Name: helloworld-mytest
Version: 0.1.3
Summary: just a test module
Home-page: UNKNOWN
Author: UNKNOWN
Author-email: UNKNOWN
License: UNKNOWN
Platform: UNKNOWN
